sphynx/__init__.py
sphynx/lib.py
sphynx-0.0.3.dist-info/LICENSE
sphynx-0.0.3.dist-info/METADATA
sphynx-0.0.3.dist-info/WHEEL
sphynx-0.0.3.dist-info/top_level.txt
sphynx-0.0.3.dist-info/RECORD
