Metadata-Version: 2.1
Name: sphynx
Version: 0.0.3
Summary: A wrapper around structlog with nice defaults
Home-page: https://github.com/senyosimpson/sphynx
Author: Senyo Simpson
Author-email: simpsonsenyo@gmail.com
License: UNKNOWN
Platform: UNKNOWN
Classifier: Programming Language :: Python :: 3
Classifier: License :: OSI Approved :: MIT License
Classifier: Operating System :: OS Independent
Requires-Python: >=3.6
